clerk/__init__.py
clerk/base.py
clerk/client.py
clerk/decorator/__init__.py
clerk/decorator/models.py
clerk/decorator/task_decorator.py
clerk/development/__init__.py
clerk/development/cli.py
clerk/development/code_runner.py
clerk/development/init_project.py
clerk/development/gui/graph_checker.py
clerk/development/gui/test_session.py
clerk/development/schema/fetch_schema.py
clerk/development/templates/exceptions.py.template
clerk/development/templates/launch.json.template
clerk/development/templates/main_basic.py.template
clerk/development/templates/main_gui.py.template
clerk/development/templates/rollbacks.py.template
clerk/development/templates/states.py.template
clerk/development/templates/tasks.json.template
clerk/development/templates/test_payload.py.template
clerk/development/templates/transitions.py.template
clerk/exceptions/__init__.py
clerk/exceptions/exceptions.py
clerk/exceptions/remote_device.py
clerk/gui_automation/__init__.py
clerk/gui_automation/client.py
clerk/gui_automation/requirements.txt
clerk/gui_automation/action_model/__init__.py
clerk/gui_automation/action_model/model.py
clerk/gui_automation/action_model/utils.py
clerk/gui_automation/client_actor/__init__.py
clerk/gui_automation/client_actor/client_actor.py
clerk/gui_automation/client_actor/exception.py
clerk/gui_automation/client_actor/model.py
clerk/gui_automation/decorators/__init__.py
clerk/gui_automation/decorators/gui_automation.py
clerk/gui_automation/exceptions/__init__.py
clerk/gui_automation/exceptions/agent_manager.py
clerk/gui_automation/exceptions/websocket.py
clerk/gui_automation/exceptions/modality/__init__.py
clerk/gui_automation/exceptions/modality/exc.py
clerk/gui_automation/ui_actions/__init__.py
clerk/gui_automation/ui_actions/actions.py
clerk/gui_automation/ui_actions/base.py
clerk/gui_automation/ui_actions/support.py
clerk/gui_automation/ui_state_inspector/__init__.py
clerk/gui_automation/ui_state_inspector/gui_vision.py
clerk/gui_automation/ui_state_inspector/models.py
clerk_sdk-0.5.3.dist-info/METADATA
clerk_sdk-0.5.3.dist-info/WHEEL
clerk_sdk-0.5.3.dist-info/entry_points.txt
clerk_sdk-0.5.3.dist-info/licenses/LICENSE
clerk_sdk-0.5.3.dist-info/RECORD
