Metadata-Version: 2.4
Name: clerk-sdk
Version: 0.5.3
Summary: Library for interacting with Clerk
Project-URL: Homepage, https://github.com/F-ONE-Group/clerk_pypi
Author-email: F-One <contact@f-one.group>
License-File: LICENSE
Classifier: License :: OSI Approved :: MIT License
Classifier: Operating System :: OS Independent
Classifier: Programming Language :: Python :: 3
Requires-Python: >=3.11
Requires-Dist: backoff<3.0.0,>=2.0.0
Requires-Dist: debugpy<2.0.0,>=1.8.0
Requires-Dist: pydantic<3.0.0,>=2.0.0
Requires-Dist: python-dotenv>=1.0.0
Requires-Dist: requests<3.0.0,>=2.32.3
Requires-Dist: rich>=14.2.0
Provides-Extra: all
Requires-Dist: networkx<4.0.0,>=3.5.0; extra == 'all'
Requires-Dist: websockets>=15.0.1; extra == 'all'
Provides-Extra: gui-automation
Requires-Dist: networkx<4.0.0,>=3.5.0; extra == 'gui-automation'
Requires-Dist: websockets>=15.0.1; extra == 'gui-automation'
